pyaudiopdf/__init__.py
pyaudiopdf-0.0.2.dist-info/LICENCE
pyaudiopdf-0.0.2.dist-info/METADATA
pyaudiopdf-0.0.2.dist-info/WHEEL
pyaudiopdf-0.0.2.dist-info/top_level.txt
pyaudiopdf-0.0.2.dist-info/RECORD
