Metadata-Version: 2.1
Name: pyaudiopdf
Version: 0.0.2
Summary: This package can read out Pdf file..
Home-page: UNKNOWN
Author: Akshat Tiwari
Author-email: thealphacoding@gmail.com
License: UNKNOWN
Platform: UNKNOWN
Classifier: Programming Language :: Python :: 3
Classifier: License :: OSI Approved :: MIT License
Classifier: Operating System :: OS Independent
Requires-Python: >=3.6
Requires-Dist: pyttsx3
Requires-Dist: pyPDF2
